varen/__init__.py
varen/body_models.py
varen/lbs.py
varen/utils.py
varen/vertex_ids.py
varen/vertex_joint_selector.py
varen-1.1.3.dist-info/licenses/LICENSE
varen-1.1.3.dist-info/METADATA
varen-1.1.3.dist-info/WHEEL
varen-1.1.3.dist-info/top_level.txt
varen-1.1.3.dist-info/RECORD
