Metadata-Version: 2.4
Name: varen
Version: 1.1.3
Summary: PyTorch module for loading the VAREN body model
Author: Silvia Zuffi
Author-email: Dennis Perrett <dennis.perrett@tuebingen.mpg.de>
License: Proprietary
Requires-Python: >=3.6.0
License-File: LICENSE
Requires-Dist: numpy>=1.16.2
Requires-Dist: torch>=1.0.1.post2
Requires-Dist: scipy>=1.0.0
Provides-Extra: trimesh
Requires-Dist: trimesh>=2.37.6; extra == "trimesh"
Requires-Dist: pyglet<2.0; extra == "trimesh"
Provides-Extra: dev
Requires-Dist: pytest; extra == "dev"
Requires-Dist: pre-commit; extra == "dev"
Provides-Extra: all
Requires-Dist: trimesh>=2.37.6; extra == "all"
Requires-Dist: pyglet<2.0; extra == "all"
Requires-Dist: pytest; extra == "all"
Requires-Dist: pre-commit; extra == "all"
Dynamic: license-file
